crawlerx/__init__.py
crawlerx/crawlerx.py
crawlerx-1.1.1.dist-info/licenses/LICENSE
crawlerx-1.1.1.dist-info/METADATA
crawlerx-1.1.1.dist-info/WHEEL
crawlerx-1.1.1.dist-info/entry_points.txt
crawlerx-1.1.1.dist-info/top_level.txt
crawlerx-1.1.1.dist-info/RECORD
