Metadata-Version: 2.4
Name: crawlerx
Version: 1.1.1
Summary: CrawlerX - The Ultimate Web Crawler
Home-page: https://github.com/IMApurbo/crawlerx
Author: AKM Korishee Apurbo
Author-email: bandinvisible8@gmail.com
License: MIT
Classifier: Programming Language :: Python :: 3
Classifier: Programming Language :: Python :: 3.7
Classifier: Programming Language :: Python :: 3.8
Classifier: Programming Language :: Python :: 3.9
Classifier: Programming Language :: Python :: 3.10
Classifier: Programming Language :: Python :: 3.11
Classifier: License :: OSI Approved :: MIT License
Classifier: Operating System :: OS Independent
Requires-Python: >=3.7
License-File: LICENSE
Requires-Dist: requests==2.32.3
Requires-Dist: beautifulsoup4==4.12.3
Requires-Dist: urllib3==2.2.3
Dynamic: author
Dynamic: author-email
Dynamic: classifier
Dynamic: description
Dynamic: description-content-type
Dynamic: home-page
Dynamic: license
Dynamic: license-file
Dynamic: requires-dist
Dynamic: requires-python
Dynamic: summary
